InstanceSuggestor/InstanceSuggestor.py
InstanceSuggestor/__init__.py
InstanceSuggestor/suggest.py
InstanceSuggestor-1.1.4.dist-info/LICENSE
InstanceSuggestor-1.1.4.dist-info/METADATA
InstanceSuggestor-1.1.4.dist-info/WHEEL
InstanceSuggestor-1.1.4.dist-info/top_level.txt
InstanceSuggestor-1.1.4.dist-info/RECORD
