Metadata-Version: 2.1
Name: InstanceSuggestor
Version: 1.1.4
Summary: A cloud instance suggestor
Home-page: https://github.com/NetBook-ai/Instance-suggestor
Author: Shruti Sharma
Author-email: shruti.sharma@netbook.ai
License: LICENSE.txt
Platform: UNKNOWN
Classifier: Programming Language :: Python
Classifier: Programming Language :: Python :: 3
Classifier: Operating System :: OS Independent
License-File: LICENSE
Requires-Dist: numpy
Requires-Dist: pandas
